{
  "cell": "SkillGen+SART",
  "source": "/peg_work/gen_skillgen.hdf5",
  "num_attempts": 300,
  "num_success": 46,
  "dgr_pct": 15.33,
  "offset_pos_std_m": 0.0218,
  "n_sources": 20,
  "n_per": 15,
  "num_envs": 15,
  "radius": 0.05,
  "rot_deg": 10.0,
  "position_fix": false,
  "k_off": 10,
  "k_interp": 20,
  "k_fixed": 5,
  "attempted_xy_std": [
    0.0551,
    0.0753
  ],
  "unique_source_xy": 20,
  "out": "/peg_work/gen_skillgen_sart.hdf5",
  "failed_out": "/peg_work/gen_skillgen_sart_failed.hdf5"
}